{
  "id": "2026-06-04-linux-arch-platform-daily",
  "topic": "linux-arch-platform",
  "title": "2026-06-04 페이지표 위치 변경 — 아키텍처·플랫폼",
  "headline": "메모리 검사 페이지표 위치와 가상화 더티 로그 준비가 아키텍처 쪽 핵심입니다.",
  "date": "2026-06-04",
  "summary": "오늘은 arm64 메모리 검사 페이지표를 별도 페이지 디렉터리 섹션으로 옮기는 흐름과, RISC-V 가상화 더티 로그 경로의 페이지 분할 캐시 추가가 가장 직접적인 신호입니다. 보안·회귀로 분류된 별도 항목은 없지만, 스택트레이스 심볼 표시와 powerpc 코드 패칭의 임시 매핑 권한 축소도 아키텍처 유지보수 관점에서 따라볼 만합니다.",
  "tags": [
    "ARM64",
    "RISC-V",
    "아키텍처"
  ],
  "highlights": [
    {
      "title": "arm64 메모리 검사 페이지표를 일반 데이터 영역 밖으로 이동",
      "priority": "상",
      "impactType": "runtime",
      "affectedAudience": "arm64 메모리 관리 담당자",
      "verifyLink": "https://lore.kernel.org/linux-arm-kernel/20260603160949.3372482-7-ardb+git@google.com/",
      "if": "arm64 메모리 검사 부팅 경로를 다룬다면",
      "do": "페이지표 섹션 배치가 자기 트리의 선형 매핑 제거 흐름과 맞는지 diff로 비교하세요",
      "verify": "링크된 패치의 섹션 배치 설명과 부팅 맵 초기화 코드를 대조하세요"
    },
    {
      "title": "RISC-V 가상화 더티 로그용 페이지 분할 캐시 추가",
      "priority": "상",
      "impactType": "runtime",
      "affectedAudience": "RISC-V KVM 유지보수자",
      "verifyLink": "https://lore.kernel.org/linux-riscv/20260603175439237VrPTLz6fG79fXRYAu-JFW@zte.com.cn/",
      "if": "RISC-V 가상 머신 더티 로그를 쓰는 환경이라면",
      "do": "더티 로그 활성화와 지우기 호출 경로의 페이지 분할 캐시 사용 지점을 grep하세요",
      "verify": "패치 스레드의 호출 경로 설명을 자기 KVM 테스트 로그와 맞춰보세요"
    },
    {
      "title": "RISC-V 스택트레이스 심볼 표시를 백트레이스용 형식으로 변경",
      "priority": "중",
      "impactType": "runtime",
      "affectedAudience": "RISC-V 디버깅·진단 담당자",
      "verifyLink": "https://lore.kernel.org/linux-riscv/20260603115329.791603-3-qirui.001@bytedance.com/",
      "if": "RISC-V 패닉 로그를 자동 분석한다면",
      "do": "스택트레이스 출력 파서가 바뀐 심볼 해석 결과를 그대로 수용하는지 재현 로그로 비교하세요",
      "verify": "링크된 패치의 출력 형식 변경과 자기 로그 파서 테스트를 대조하세요"
    },
    {
      "title": "powerpc 코드 패칭 임시 매핑을 읽기 전용으로 축소",
      "priority": "중",
      "impactType": "security",
      "affectedAudience": "powerpc 코드 패칭 담당자",
      "verifyLink": "https://lore.kernel.org/linux-arm-kernel/aiBsMg9WdDy-dRk_@li-1a3e774c-28e4-11b2-a85c-acc9f2883e29.ibm.com/",
      "if": "powerpc 코드 패칭 경로를 유지한다면",
      "do": "제로 페이지 임시 매핑이 읽기 전용 호출로 바뀌는지 패치와 자기 트리를 diff로 비교하세요",
      "verify": "스레드와 maintainer 적용 코멘트를 함께 보고 후속 const 변경 의존성을 확인하세요"
    }
  ],
  "sections": [
    {
      "heading": "릴리스/로드맵",
      "body": "이 렌즈는 리스트 중심입니다. 입력 초안에 kernel.org 릴리스 항목이 없어 오늘은 메인라인 릴리스나 장기 지원 릴리스 요약을 추가하지 않습니다."
    },
    {
      "heading": "회귀·보안 신호",
      "body": "- powerpc 코드 패칭 임시 매핑 권한 축소\n  · 영향: 제로 페이지를 쓰기 가능 임시 매핑으로 만들던 경로를 읽기 전용 매핑으로 단순화해, 이후 empty_zero_page를 const 데이터로 바꾸는 흐름을 준비합니다.\n  · 확인: https://lore.kernel.org/linux-arm-kernel/aiBsMg9WdDy-dRk_@li-1a3e774c-28e4-11b2-a85c-acc9f2883e29.ibm.com/\n\n- 회귀로 명시 분류된 항목 없음\n  · 영향: 입력 후보 안에서는 회귀 태그나 실패 보고보다 아키텍처 내부 정리와 런타임 동작 보정이 중심입니다.\n  · 확인: 입력 sources의 각 lore 스레드에서 후속 답장을 추적하세요."
    },
    {
      "heading": "핵심 변경",
      "body": "- arm64 메모리 검사 페이지표를 일반 데이터 영역 밖으로 이동\n  · 영향: 일반 메모리 검사 페이지표를 가능한 경우 .pgdir 섹션에 배치하고, 아키텍처가 해당 섹션을 제공하지 않으면 페이지 정렬된 BSS로 되돌리는 변경입니다. 배경은 BSS 자체가 더 이상 선형 매핑으로 접근 가능하지 않다는 점입니다.\n  · 확인: https://lore.kernel.org/linux-arm-kernel/20260603160949.3372482-7-ardb+git@google.com/\n\n- RISC-V 가상화 더티 로그 호출 경로에 페이지 분할 캐시 추가\n  · 영향: 더티 로그 활성화와 KVM_CLEAR_DIRTY_LOG ioctl 경로에서 페이지 분할 작업을 위한 캐시를 추가하는 제안입니다. 사용자 ABI 자체를 새로 만든다기보다 ioctl 처리 중 내부 메모리 작업 비용과 준비 상태에 영향을 줄 수 있습니다.\n  · 확인: https://lore.kernel.org/linux-riscv/20260603175439237VrPTLz6fG79fXRYAu-JFW@zte.com.cn/\n\n- RISC-V 스택트레이스 출력의 심볼 해석 보정\n  · 영향: noreturn 함수 뒤 저장된 반환 주소가 다음 함수 시작을 가리켜 잘못된 심볼로 풀리는 문제를 줄이기 위해, 스택 백트레이스용 주소 형식을 사용하도록 바꿉니다.\n  · 확인: https://lore.kernel.org/linux-riscv/20260603115329.791603-3-qirui.001@bytedance.com/"
    },
    {
      "heading": "기타",
      "body": "- PolarFire SoC 온도·전압 센서 드라이버 추가\n  · 영향: 다이 온도와 1.05, 1.8, 2.5 볼트 레일을 노출하지만, 알람은 한 번 발생하면 지울 수 없는 하드웨어 erratum 때문에 지원하지 않습니다. 단일 SoC 장치 지원 성격이 강해 플랫폼 관심사로만 낮게 봅니다.\n  · 확인: https://lore.kernel.org/linux-riscv/20260603-ongoing-brunette-51e35be6d93e@spud/\n\n- Khadas VIM4 MCU와 팬 지원\n  · 영향: VIM4 보드의 다른 MCU 변형, 팬 단계 범위, 팬 전원 레귤레이터를 반영하는 MFD·팬·DTS 변경입니다. 보드별 지원이므로 해당 보드를 쓰는 팀만 추적하면 됩니다.\n  · 확인: https://lore.kernel.org/linux-arm-kernel/20260603-add-mcu-fan-khadas-vim4-v7-0-594ba8a965d8@aliel.fr/"
    }
  ],
  "confidence": {
    "level": "자동 생성",
    "note": "AI가 원문 후보와 메타데이터를 요약했습니다. 중요한 판단 전에는 링크된 원문을 확인하세요."
  },
  "sources": [
    {
      "title": "arm64: Move generic KASAN page tables out of BSS too",
      "url": "https://lore.kernel.org/linux-arm-kernel/20260603160949.3372482-7-ardb+git@google.com/",
      "note": "lore.kernel.org/linux-arm-kernel · patch-discussion"
    },
    {
      "title": "hwmon: add a driver for the temp/voltage sensor on PolarFire SoC",
      "url": "https://lore.kernel.org/linux-riscv/20260603-ongoing-brunette-51e35be6d93e@spud/",
      "note": "lore.kernel.org/linux-riscv · patch-discussion"
    },
    {
      "title": "riscv: stacktrace: Use %pB for backtrace display",
      "url": "https://lore.kernel.org/linux-riscv/20260603115329.791603-3-qirui.001@bytedance.com/",
      "note": "lore.kernel.org/linux-riscv · patch-discussion"
    },
    {
      "title": "RISC-V: KVM: Add the split page cache for ioctl context",
      "url": "https://lore.kernel.org/linux-riscv/20260603175439237VrPTLz6fG79fXRYAu-JFW@zte.com.cn/",
      "note": "lore.kernel.org/linux-riscv · patch-discussion"
    },
    {
      "title": "powerpc/code-patching: Avoid r/w mapping of the zero page",
      "url": "https://lore.kernel.org/linux-arm-kernel/aiBsMg9WdDy-dRk_@li-1a3e774c-28e4-11b2-a85c-acc9f2883e29.ibm.com/",
      "note": "lore.kernel.org/linux-arm-kernel · patch-discussion"
    },
    {
      "title": "Add VIM4 MCU/FAN support",
      "url": "https://lore.kernel.org/linux-arm-kernel/20260603-add-mcu-fan-khadas-vim4-v7-0-594ba8a965d8@aliel.fr/",
      "note": "lore.kernel.org/linux-arm-kernel · patch-discussion"
    }
  ],
  "draftMetadata": {
    "generatedAt": "2026-06-03T18:18:16.725Z",
    "sourceRecordCount": 50,
    "candidateCount": 6,
    "generator": "scripts/draft-lore-lens.mjs",
    "candidateIds": [
      "lore-linux-arm-kernel:urn:uuid:09c66936-30a8-1f62-49f2-39223618965e",
      "lore-linux-riscv:urn:uuid:5a2dd355-9e53-541a-bd73-f9366ea0c93d",
      "lore-linux-riscv:urn:uuid:57f204b6-1b12-ae66-1a8e-b17c042770e7",
      "lore-linux-riscv:urn:uuid:f2e8b1c4-67bb-311c-6e63-a057449c6c19",
      "lore-linux-arm-kernel:urn:uuid:26582fa0-00cd-8354-3f48-370cf3d17280",
      "lore-linux-arm-kernel:urn:uuid:94054029-bb7f-791a-f2bd-9191e7e36a33"
    ],
    "bucketCounts": {
      "releases": 0,
      "regressions": 0,
      "patches": 6,
      "otherSignals": 0
    },
    "lensSignalCount": 6,
    "signalLevel": "high",
    "subsystems": [
      "메모리 관리"
    ],
    "lensPipeline": "linux-arch-platform",
    "rewrittenAt": "2026-06-03T18:18:23.245Z",
    "rewriteAdapter": "codex",
    "promptTemplate": "prompts/linux-lens-newsletter-ko.md"
  }
}