{
  "topic": "opensource",
  "runDate": "2026-06-03",
  "startedAt": "2026-06-02T18:02:44.858Z",
  "finishedAt": "2026-06-02T18:03:52.344Z",
  "ok": true,
  "steps": [
    {
      "name": "collect",
      "command": "npm run collect:opensource",
      "startedAt": "2026-06-02T18:02:44.859Z",
      "finishedAt": "2026-06-02T18:02:49.496Z",
      "code": 0,
      "ok": true,
      "stdout": "> dev-blog@0.1.0 collect:opensource\n> node scripts/collect-opensource.mjs\n\nCollected 63 unique opensource record(s); github-recent-stars 30; github-active-popular 30; hn-frontpage-github 3; wrote data/normalized/opensource/source-records-latest.json",
      "stderr": ""
    },
    {
      "name": "draft",
      "command": "npm run draft:opensource",
      "startedAt": "2026-06-02T18:02:49.496Z",
      "finishedAt": "2026-06-02T18:02:51.346Z",
      "code": 0,
      "ok": true,
      "stdout": "> dev-blog@0.1.0 draft:opensource\n> node scripts/draft-opensource.mjs\n\nSelected 13 opensource candidate(s) from 63 source record(s); wrote data/generated/opensource/2026-06-03-opensource-trending.json",
      "stderr": ""
    },
    {
      "name": "rewrite",
      "command": "npm run rewrite:opensource:codex",
      "startedAt": "2026-06-02T18:02:51.346Z",
      "finishedAt": "2026-06-02T18:03:51.563Z",
      "code": 0,
      "ok": true,
      "stdout": "> dev-blog@0.1.0 rewrite:opensource:codex\n> AI_ADAPTER=codex node scripts/ai-rewrite-opensource.mjs\n\nRewrote opensource trending with codex adapter; wrote data/generated/opensource/rewritten-2026-06-03-opensource-trending.json",
      "stderr": ""
    },
    {
      "name": "publish",
      "command": "npm run publish:opensource",
      "startedAt": "2026-06-02T18:03:51.563Z",
      "finishedAt": "2026-06-02T18:03:51.860Z",
      "code": 0,
      "ok": true,
      "stdout": "> dev-blog@0.1.0 publish:opensource\n> node scripts/publish-opensource.mjs\n\nPublished opensource trending: content/topics/opensource/posts/2026-06-03-opensource-trending.json",
      "stderr": ""
    },
    {
      "name": "build",
      "command": "npm run build",
      "startedAt": "2026-06-02T18:03:51.860Z",
      "finishedAt": "2026-06-02T18:03:52.344Z",
      "code": 0,
      "ok": true,
      "stdout": "> dev-blog@0.1.0 build\n> node scripts/build-site.mjs\n\nBuilt 11 topic(s), 257 post(s), 130 tag(s) into public/",
      "stderr": ""
    }
  ],
  "publishEnabled": true
}